powertools/__init__.py
powertools/__main__.py
powertools/_version.py
powertools/py.typed
powertools/cli/__init__.py
powertools/cli/embed.py
powertools/cli/init.py
powertools/cli/main.py
powertools/cli/memory.py
powertools/cli/tasks.py
powertools/core/__init__.py
powertools/core/config.py
powertools/core/embeddings.py
powertools/core/memory.py
powertools/core/tasks.py
powertools/embed/__init__.py
powertools/embed/daemon.py
powertools/embed/server.py
powertools/mcp/__init__.py
powertools/mcp/memory.py
powertools/mcp/server.py
powertools/mcp/tasks.py
powertools/storage/__init__.py
powertools/storage/jsonl.py
powertools/storage/qdrant.py
powertools/templates/__init__.py
powertools/templates/agents_section.md
powertools/templates/compose.yaml
powertools_ai-1.1.2.dist-info/METADATA
powertools_ai-1.1.2.dist-info/WHEEL
powertools_ai-1.1.2.dist-info/entry_points.txt
powertools_ai-1.1.2.dist-info/licenses/LICENSE
powertools_ai-1.1.2.dist-info/RECORD
