Metadata-Version: 2.4
Name: powertools-ai
Version: 1.1.2
Summary: Agentic workflow toolkit with persistent memory and task tracking
Author-email: Sumit Arora <sumit@fincognition.com>
License: MIT
License-File: LICENSE
Keywords: agents,ai,mcp,memory,tasks
Classifier: Development Status :: 3 - Alpha
Classifier: Intended Audience :: Developers
Classifier: License :: OSI Approved :: MIT License
Classifier: Programming Language :: Python :: 3.12
Classifier: Programming Language :: Python :: 3.13
Requires-Python: >=3.12
Requires-Dist: click>=8.1.0
Requires-Dist: fastyaml-rs>=0.3.0
Requires-Dist: httpx>=0.27.0
Requires-Dist: mcp>=1.0.0
Requires-Dist: orjson>=3.9.0
Requires-Dist: pydantic>=2.0.0
Requires-Dist: qdrant-client>=1.12.0
Requires-Dist: rich>=13.0.0
Requires-Dist: starlette>=0.41.0
Requires-Dist: uvicorn>=0.32.0
Provides-Extra: dev
Requires-Dist: mypy>=1.13.0; extra == 'dev'
Requires-Dist: pytest-asyncio>=0.24.0; extra == 'dev'
Requires-Dist: pytest-cov>=5.0.0; extra == 'dev'
Requires-Dist: pytest>=8.0.0; extra == 'dev'
Requires-Dist: python-semantic-release==10.5.3; extra == 'dev'
Requires-Dist: ruff>=0.8.0; extra == 'dev'
Requires-Dist: types-pyyaml>=6.0.0; extra == 'dev'
Provides-Extra: mlx
Requires-Dist: mlx-embeddings>=0.0.5; extra == 'mlx'
